shortesttrack_tools/__init__.py
shortesttrack_tools/api_client/__init__.py
shortesttrack_tools/api_client/base_api_client.py
shortesttrack_tools/api_client/public_key_mixin.py
shortesttrack_tools/api_client/sec_access_token_mixin.py
shortesttrack_tools/api_client/sec_refresh_token_mixin.py
shortesttrack_tools/api_client/endpoints/__init__.py
shortesttrack_tools/api_client/endpoints/base_endpoint.py
shortesttrack_tools/api_client/endpoints/data.py
shortesttrack_tools/api_client/endpoints/endpoint_urls.py
shortesttrack_tools/api_client/endpoints/exec_api.py
shortesttrack_tools/api_client/endpoints/exec_scheduler.py
shortesttrack_tools/api_client/endpoints/logging.py
shortesttrack_tools/api_client/endpoints/metadata.py
shortesttrack_tools/classproperty/__init__.py
shortesttrack_tools/enums/__init__.py
shortesttrack_tools/enums/log_level.py
shortesttrack_tools/functional/__init__.py
shortesttrack_tools/functional/cached_property.py
shortesttrack_tools/functional/classproperty.py
shortesttrack_tools/jwt_util/__init__.py
shortesttrack_tools/jwt_util/jwt_util.py
shortesttrack_tools/logger/__init__.py
shortesttrack_tools/logger/channels.py
shortesttrack_tools/logger/utils.py
shortesttrack_tools/logger/clients/__init__.py
shortesttrack_tools/logger/clients/base_logger_client.py
shortesttrack_tools/logger/clients/prototype_client.py
shortesttrack_tools/logger/handlers/__init__.py
shortesttrack_tools/logger/handlers/st_handler.py
shortesttrack_tools/logger/registry/__init__.py
shortesttrack_tools/logger/registry/logger_registry.py
shortesttrack_tools/tests/__init__.py
shortesttrack_tools/tests/test_api_client.py
shortesttrack_tools/tests/_utils/__init__.py
shortesttrack_tools/tests/_utils/mock_classes.py
shortesttrack_tools/tests/_utils/t_case_mixins.py
shortesttrack_tools/unique/__init__.py
shortesttrack_tools/unique/unique.py
shortesttrack_tools-0.1.10.dist-info/METADATA
shortesttrack_tools-0.1.10.dist-info/WHEEL
shortesttrack_tools-0.1.10.dist-info/top_level.txt
shortesttrack_tools-0.1.10.dist-info/RECORD
