Metadata-Version: 2.1
Name: shortesttrack-tools
Version: 0.1.10
Summary: UNKNOWN
Home-page: UNKNOWN
Author: UNKNOWN
Author-email: UNKNOWN
License: UNKNOWN
Platform: UNKNOWN
Requires-Dist: URLObject (==2.4.3)
Requires-Dist: requests (==2.19.1)
Requires-Dist: requests-oauthlib (==1.0.0)
Requires-Dist: pytz (==2018.5)
Requires-Dist: PyJWT (==1.6.1)
Requires-Dist: cryptography (==2.2.1)
